juice_scheduler/__init__.py
juice_scheduler/common/__init__.py
juice_scheduler/common/date_utils.py
juice_scheduler/common/event_period.py
juice_scheduler/common/interval.py
juice_scheduler/model/__init__.py
juice_scheduler/model/events.py
juice_scheduler/model/mission_phase.py
juice_scheduler/model/segment_definition.py
juice_scheduler/model/segment_list.py
juice_scheduler/model/segmentation.py
juice_scheduler/model/working_group.py
juice_scheduler/py.typed
juice_scheduler-0.0.1.dist-info/LICENSE
juice_scheduler-0.0.1.dist-info/METADATA
juice_scheduler-0.0.1.dist-info/WHEEL
juice_scheduler-0.0.1.dist-info/RECORD
