Metadata-Version: 2.1
Name: juice-scheduler
Version: 0.0.1
Summary: JUICE Scheduler is a Python package that provides a library and command line tools to support the JUICE mission science planning.
Home-page: https://juicesoc.esac.esa.int/data/juice-scheduler
License: MIT
Author: JUICE SOC Team
Author-email: juice_soc@cosmos.esa.int
Requires-Python: >=3.8.1,<4.0
Classifier: Development Status :: 4 - Beta
Classifier: Intended Audience :: Developers
Classifier: License :: OSI Approved :: MIT License
Classifier: Operating System :: OS Independent
Classifier: Programming Language :: Python
Classifier: Programming Language :: Python :: 3
Classifier: Programming Language :: Python :: 3.9
Classifier: Programming Language :: Python :: 3.10
Classifier: Programming Language :: Python :: 3.11
Classifier: Programming Language :: Python :: 3.12
Classifier: Programming Language :: Python :: 3.8
Classifier: Topic :: Software Development :: Libraries :: Python Modules
Classifier: Typing :: Typed
Requires-Dist: portion (>=2.6.0,<3.0.0)
Requires-Dist: pytz (>=2025.1,<2026.0)
Project-URL: Documentation, https://juicesoc.esac.esa.int/data/juice-scheduler
Project-URL: Repository, https://juigitlab.esac.esa.int/core-system/uplink/juice-scheduler
